realign/__init__.py
realign/agents.py
realign/configs.py
realign/datasets.py
realign/defaults.yaml
realign/evaluators.py
realign/llm_utils.py
realign/router.py
realign/simulation.py
realign/templates.yaml
realign/utils.py
realign/evallib/__init__.py
realign/evallib/checkers.py
realign/evallib/hf.py
realign/evallib/llm.py
realign/evallib/nlp.py
realign/evallib/py.py
realign/evallib/rag.py
realign/evallib/serp.py
realign/evallib/stats.py
realign/realtime/controller.py
realign/realtime/event.py
realign/realtime/main.py
realign/realtime/process.py
realign/realtime/state.py
realign/realtime/tsafepq.py
realign-0.1.48.dist-info/LICENSE
realign-0.1.48.dist-info/METADATA
realign-0.1.48.dist-info/WHEEL
realign-0.1.48.dist-info/top_level.txt
realign-0.1.48.dist-info/RECORD
