Metadata-Version: 2.1
Name: realign
Version: 0.1.48
Summary: Realign is a simulation based evaluation framework for multi-step agents.
Author-email: HoneyHive <support@honeyhive.ai>
License: MIT License
Project-URL: Documentation, https://docs.honeyhive.ai/
Classifier: Development Status :: 3 - Alpha
Classifier: Intended Audience :: Developers
Classifier: Natural Language :: English
Classifier: License :: OSI Approved :: MIT License
Classifier: Programming Language :: Python
Classifier: Programming Language :: Python :: 3
Classifier: Programming Language :: Python :: 3.7
Classifier: Programming Language :: Python :: 3.8
Classifier: Programming Language :: Python :: 3.9
Classifier: Programming Language :: Python :: 3.10
Classifier: Programming Language :: Python :: 3.11
Classifier: Programming Language :: Python :: 3.12
Classifier: Programming Language :: Python :: 3.13
Requires-Python: >=3.9
License-File: LICENSE
Requires-Dist: litellm
Requires-Dist: jinja2
Requires-Dist: python-dotenv
Provides-Extra: dev
Requires-Dist: pylint==2.16.2; extra == "dev"
Requires-Dist: pip-tools>=7.4.1; extra == "dev"
Provides-Extra: personas
Requires-Dist: llama-index<0.11.0,>=0.10.56; extra == "personas"
